{
  "op": "UpsampleNearest3d",
  "repo": "ops-cv",
  "hardware": [
    "Atlas A2",
    "Atlas A3"
  ],
  "reference": {
    "type": "builtin",
    "ref": "仓内既有 Ascend C 实现 ops-cv image/upsample_nearest3d（op_def 算子名 UpsampleNearest3d）；本任务是在其上增开 uint8 通路",
    "path": "repos/ops-cv/image/upsample_nearest3d/{op_host,op_kernel}"
  },
  "change": {
    "kind": "add_dtype",
    "dtypes_added": [
      "uint8"
    ],
    "note": "任务书『使其支持unit8(sic, = uint8)数据类型』；语义（最近邻、无半像素项）不变，只加 dtype"
  },
  "params_source": "task_doc_table",
  "params": [
    {
      "name": "self",
      "io": "in",
      "dtype": [
        "float32",
        "float16",
        "bfloat16"
      ],
      "rank": 5,
      "noncontiguous": true
    },
    {
      "name": "output_size",
      "io": "attr",
      "dtype": [
        "list_int"
      ],
      "default": [
        4,
        6,
        8
      ]
    },
    {
      "name": "scale_d",
      "io": "attr",
      "dtype": [
        "double"
      ],
      "default": 0.0
    },
    {
      "name": "scale_h",
      "io": "attr",
      "dtype": [
        "double"
      ],
      "default": 0.0
    },
    {
      "name": "scale_w",
      "io": "attr",
      "dtype": [
        "double"
      ],
      "default": 0.0
    },
    {
      "name": "out",
      "io": "out",
      "dtype": [
        "float32",
        "float16",
        "bfloat16"
      ]
    }
  ],
  "generalize": true,
  "dtype_required": [
    "float32",
    "float16",
    "bfloat16",
    "double",
    "uint8"
  ],
  "dtype_tested": [
    "float32",
    "float16",
    "bfloat16"
  ],
  "verify_mode": "numerical",
  "precision": {
    "oracle": "ascendoptest",
    "standard": "ascendoptest_default",
    "tolerance_policy_id": "ascendoptest_default",
    "threshold": 0.001,
    "policy": {
      "kind": "ascendoptest_default",
      "tolerance": 0.001,
      "error_rate": 0.001,
      "eps": 1e-09,
      "legacy": 0.1,
      "not_settled": false
    },
    "policy_note": "spec 级 policy 为主 dtype(fp16) 代表；per-case policy 由 gen_cases 按 golden dtype 派生(fp32=1e-4/fp16=1e-3)",
    "threshold_source": "任务书『算子计算精度需满足 AscendOpTest 工具默认阈值』无数值；0.001 为 fp16 惯例 (推断/待工具核实)。注：最近邻插值是纯 gather，输出恒为输入元素的逐位拷贝、理论上应精确相等，此阈值实际是宽松上界",
    "case_target": 20,
    "bf16_bitexact": true
  },
  "perf": {
    "baseline": "tbe",
    "target_ratio": 0.95,
    "target_ratio_source": "任务书性能要求『uint8性能和fp16数据类型比，劣化5%之内』→ 0.95",
    "small_shape_exception": {
      "text": "<10us 差 3us→仿真图",
      "when_us_below": 10,
      "abs_gap_us_within": 3,
      "requires": "simulation_plot+analysis"
    }
  },
  "task_pr_gaps": [
    {
      "kind": "dtype_unsupported_by_op_def",
      "dtypes": [
        "uint8",
        "double"
      ],
      "op_def_dtypes": [
        "float32",
        "float16",
        "bfloat16"
      ],
      "task_doc_ref": "repos/cann-ops-competitions/04_tasks/01_community-task-2026/docs/202605/UpsampleNearest3d_task_doc.md:6（适配硬件 = Atlas A2 训练系列产品/Atlas A3 系列产品）+ :26,:31（self/out 数据类型列 = FLOAT32、FLOAT16、BFLOAT16、DOUBLE、UINT8）",
      "op_def_ref": "repos/ops-cv/image/upsample_nearest3d/op_host/upsample_nearest3d_def.cpp:31,37（默认 config 的 Input x / Output y DataType 只有 {DT_FLOAT, DT_FLOAT16, DT_BF16}）+ :46-47（该默认 config 挂在 AddConfig(\"ascend910b\") 与 AddConfig(\"ascend910_93\")，即任务书点名的 A2/A3 两支）",
      "reason": "**task↔op_def 冲突，本轮实读确认**：uint8 与 double 确实出现在 op_def 里，但只在 :19-21 的 xDtype 向量 → :71-72 的 regbaseConfig → :77 `AddConfig(\"ascend950\")` 那一支；而任务书 :6 的适配硬件是 A2/A3，对应 :46-47 的默认 config，那两支仍只有三浮点。按用户 2026-07-22 拍板：**任务书为准**（A2/A3），差额挂账。op_def_dtypes 字段填的是 **A2/A3 两支实际声明的集合**（不含 950 支），故与 dtypes 无交集、不自相矛盾。另 gen_cases 本轮 dtype 白名单只有 {float32,float16,int16,int32,bfloat16}，uint8/double 即便 op_def 支持了也需先扩 gen_cases+runner"
    },
    "【bf16 defer 已解除·2026-07-23】【已解除（2026-07-23）】原文：bf16 被 `gen_cases._BF16_EXACT_OPS` 这张**引擎内置的算子名白名单**（只含 Sign/Neg）挡住——任务书与 op_def 都支持 bf16，最近邻/搬运类是纯 gather、输出恒为输入元素的逐位拷贝，bf16 网格上本就精确可表示、够格进白名单，但白名单写死在引擎里、spec 无处声明。**现改由 spec 声明 `precision.bf16_bitexact: true`**，本 spec 已声明并把 bfloat16 加回 dtype 集，实测能造出 bf16 数值用例。⚠ 声明的语义是「输出恒等于某个输入元素、不做算术」——**不是放松阈值的旋钮**，声明错了会让本该用 lossy 阈值的算子被按逐位相等判。",
    "rank 5 阻塞（本轮实跑撞上的硬阻塞、且发生在 --dry-run 阶段）：本算子输入恒 5 维（任务书 :26『维度(shape) 5』），spec 按契约 C3 声明 rank=5；但 gen_cases 的 `_REG_SHAPES` 阶梯最高只到 4 维（(2,2,2,2)），`_shape_ladder` 过滤后常规 shape 为空 → fail-closed『input_rank 约束 [5] 过滤后无合法常规 shape』。这是引擎侧 shape 阶梯的覆盖缺口，须给 `_REG_SHAPES` 补 5 维（及以上）阶梯才能跑；**不得**靠把 rank 降到 4 来绕（那是改真实语义迁就引擎）",
    "任务书两处把 uint8 误拼作 unit8（:13 任务概述、:19 功能实现要求）；参数表 :26/:31 拼写正确。本 spec 按 UINT8 取值",
    "attr 名歧义：op_def 的属性名是 `output_size` + `scale_d`/`scale_h`/`scale_w`（upsample_nearest3d_def.cpp:41-44，单数 scale_），而任务书 :28-30 与 aclnn 签名用的是 scalesD/scalesH/scalesW；同仓 2d 算子又是 `scales_h`/`scales_w`（复数 scales_）。本 spec 按 **op_def 名**填（manifest/runner 侧以它为准），三套名字的差异记账在此",
    "output_size 在 op_def 里是 OPTIONAL（upsample_nearest3d_def.cpp:41），且 infershape.cpp:48,58,70 明确 output_size 与 scales **二选一**（『only one of attr::output_size or attr::scales should be defined as a non-empty value』）。本 spec 走 output_size 通路、三个 scale_* 恒 0.0；scales 通路未建模，golden 遇非 0 scale 即 fail-closed",
    "空 Tensor 冲突（**第二个** blocker，rank 5 之后紧接着就撞上）：任务书 :26/:31 明写『不支持空Tensor』『shape的C、D、H、W维的size大于0』，但 gen_cases 的 `_special_entries`（opbase §1.4）**无条件**为每个 dtype 强制注入一条 `empty` 用例。spec 没有『本算子不支持空 Tensor』的表达位 → golden 只能 fail-closed。已用探针（进程内给 `_REG_SHAPES` 临时补 5 维阶梯）验证：绕过 rank 5 后，下一条挡路的就是 (1,1,1,1,0) 这条 empty 用例，与 UpsampleNearestExact2d 同一 root cause",
    "性能基线口径与引擎槽位不符：任务书要求的是『uint8 对比同算子 fp16』的**跨 dtype 自比**，而 spec.perf.baseline 的取值域只有 {tbe, gpu_external}。本轮 uint8 未测 → 该性能要求实际无法行使；填 tbe 只是占位",
    "op_def 另有 ascend310p / kirinx90 / kirin9030 三个 config（upsample_nearest3d_def.cpp:66-68），dtype 更窄（只 {FLOAT16, FLOAT}，见 :58,:63）。本 spec 的 hardware 只取任务书『适配硬件』的 A2/A3，未覆盖这三支；950 支（:77）亦不在本 spec 口径内",
    "PR 缺口（沿用 doc/oprunway-task-pr-map.md:60,68）：本任务未找到离散交付 PR，uint8 据记载混在 Dec-2025 的批量 PR #90 里 —— 意味着『被测物是哪次改动』尚未锁定，验收前须先定 PR 口径"
  ],
  "allow_empty_tensor": false
}